CHANGES.rst
COPYING
LICENSE
MANIFEST.in
README.rst
setup.py
bin/sIBL_GUI
docs/donations/Make_A_Donation.html
docs/donations/Make_A_Donation.rst
docs/donations/resources/pictures/sIBL_GUI_Logo.png
docs/help/index.html
docs/help/sIBL_GUI_Manual.html
docs/help/sIBL_GUI_Manual.rst
docs/help/sIBL_GUI_Manual_Body.html
docs/help/resources/pictures/sIBL_GUI_About.jpg
docs/help/resources/pictures/sIBL_GUI_CachesOperations.jpg
docs/help/resources/pictures/sIBL_GUI_CollectionsOutliner.jpg
docs/help/resources/pictures/sIBL_GUI_CollectionsOutlinerAddCollection.jpg
docs/help/resources/pictures/sIBL_GUI_CollectionsOutlinerContextMenu.jpg
docs/help/resources/pictures/sIBL_GUI_ComponentsManagerUi.jpg
docs/help/resources/pictures/sIBL_GUI_ComponentsManagerUiContextMenu.jpg
docs/help/resources/pictures/sIBL_GUI_DatabaseOperations.jpg
docs/help/resources/pictures/sIBL_GUI_DownloadManager.jpg
docs/help/resources/pictures/sIBL_GUI_EditCentricLayout.jpg
docs/help/resources/pictures/sIBL_GUI_EmptyDatabaseWizard_A.jpg
docs/help/resources/pictures/sIBL_GUI_EmptyDatabaseWizard_B.jpg
docs/help/resources/pictures/sIBL_GUI_GpsMap.jpg
docs/help/resources/pictures/sIBL_GUI_IblSetsOutliner.jpg
docs/help/resources/pictures/sIBL_GUI_IblSetsOutlinerContextMenu.jpg
docs/help/resources/pictures/sIBL_GUI_IblSetsOutlinerDetailsView.jpg
docs/help/resources/pictures/sIBL_GUI_IblSetsOutlinerSearchWidgetContextMenu.jpg
docs/help/resources/pictures/sIBL_GUI_ImagesPreviewer.jpg
docs/help/resources/pictures/sIBL_GUI_InspectCentricLayout.jpg
docs/help/resources/pictures/sIBL_GUI_Inspector.jpg
docs/help/resources/pictures/sIBL_GUI_InspectorContextMenu.jpg
docs/help/resources/pictures/sIBL_GUI_LayoutsContextMenu.jpg
docs/help/resources/pictures/sIBL_GUI_LoaderScript.jpg
docs/help/resources/pictures/sIBL_GUI_LoaderScriptOptions.jpg
docs/help/resources/pictures/sIBL_GUI_LocationsBrowser.jpg
docs/help/resources/pictures/sIBL_GUI_Logo.png
docs/help/resources/pictures/sIBL_GUI_MiscellaneousContextMenu.jpg
sIBL_GUI.egg-info/PKG-INFO
sIBL_GUI.egg-info/SOURCES.txt
sIBL_GUI.egg-info/dependency_links.txt
sIBL_GUI.egg-info/requires.txt
sIBL_GUI.egg-info/top_level.txt
