Metadata-Version: 1.1
Name: sIBL-GUI
Version: 4.0.8
Summary: sIBL_GUI is an open source lighting assistant making the Image Based Lighting process easier and straight forward through the use of "Smart Ibl" files.
Home-page: https://github.com/KelSolaar/sIBL_GUI
Author: Thomas Mansencal
Author-email: thomas.mansencal@gmail.com
License: GPLv3
Platform: UNKNOWN
Classifier: Development Status :: 5 - Production/Stable
Classifier: Environment :: Console
Classifier: Environment :: MacOS X
Classifier: Environment :: Win32 (MS Windows)
Classifier: Environment :: X11 Applications :: Qt
Classifier: Intended Audience :: Developers
Classifier: Intended Audience :: Other Audience
Classifier: License :: OSI Approved :: GNU General Public License v3 (GPLv3)
Classifier: Natural Language :: English
Classifier: Operating System :: OS Independent
Classifier: Programming Language :: Python :: 2.7
Classifier: Topic :: Utilities
